{
    "land_rate": 15,
    "land_encounters": [
        {
            "level": 47,
            "species": "SPECIES_MAMOSWINE"
        },
        {
            "level": 47,
            "species": "SPECIES_SCEPTILE"
        },
        {
            "level": 49,
            "species": "SPECIES_BLAZIKEN"
        },
        {
            "level": 48,
            "species": "SPECIES_WALREIN"
        },
        {
            "level": 50,
            "species": "SPECIES_AGGRON"
        },
        {
            "level": 48,
            "species": "SPECIES_TYPHLOSION"
        },
        {
            "level": 50,
            "species": "SPECIES_INFERNAPE"
        },
        {
            "level": 49,
            "species": "SPECIES_CHARIZARD"
        },
        {
            "level": 50,
            "species": "SPECIES_CROBAT"
        },
        {
            "level": 50,
            "species": "SPECIES_PORYGON_Z"
        },
        {
            "level": 50,
            "species": "SPECIES_RHYPERIOR"
        },
        {
            "level": 50,
            "species": "SPECIES_MAGNEZONE"
        }
    ],
    "swarms": [
        "SPECIES_CROBAT",
        "SPECIES_PORYGON_Z"
    ],
    "day": [
        "SPECIES_MAMOSWINE",
        "SPECIES_SCEPTILE"
    ],
    "night": [
        "SPECIES_BLAZIKEN",
        "SPECIES_WALREIN"
    ],
    "radar": [
        "SPECIES_AGGRON",
        "SPECIES_TYPHLOSION",
        "SPECIES_INFERNAPE",
        "SPECIES_CHARIZARD"
    ],
    "rate_form0": 100,
    "rate_form1": 100,
    "rate_form2": 0,
    "rate_form3": 0,
    "rate_form4": 0,
    "unown_table": 0,
    "ruby": [
        "SPECIES_STEELIX",
        "SPECIES_GABITE"
    ],
    "sapphire": [
        "SPECIES_STEELIX",
        "SPECIES_GABITE"
    ],
    "emerald": [
        "SPECIES_STEELIX",
        "SPECIES_GABITE"
    ],
    "firered": [
        "SPECIES_STEELIX",
        "SPECIES_GABITE"
    ],
    "leafgreen": [
        "SPECIES_STEELIX",
        "SPECIES_GABITE"
    ],
    "surf_rate": 0,
    "surf_encounters": [
        {
            "level_max": 0,
            "level_min": 0,
            "species": "SPECIES_NONE"
        },
        {
            "level_max": 0,
            "level_min": 0,
            "species": "SPECIES_NONE"
        },
        {
            "level_max": 0,
            "level_min": 0,
            "species": "SPECIES_NONE"
        },
        {
            "level_max": 0,
            "level_min": 0,
            "species": "SPECIES_NONE"
        },
        {
            "level_max": 0,
            "level_min": 0,
            "species": "SPECIES_NONE"
        }
    ],
    "old_rod_rate": 0,
    "old_rod_encounters": [
        {
            "level_max": 0,
            "level_min": 0,
            "species": "SPECIES_NONE"
        },
        {
            "level_max": 0,
            "level_min": 0,
            "species": "SPECIES_NONE"
        },
        {
            "level_max": 0,
            "level_min": 0,
            "species": "SPECIES_NONE"
        },
        {
            "level_max": 0,
            "level_min": 0,
            "species": "SPECIES_NONE"
        },
        {
            "level_max": 0,
            "level_min": 0,
            "species": "SPECIES_NONE"
        }
    ],
    "good_rod_rate": 0,
    "good_rod_encounters": [
        {
            "level_max": 0,
            "level_min": 0,
            "species": "SPECIES_NONE"
        },
        {
            "level_max": 0,
            "level_min": 0,
            "species": "SPECIES_NONE"
        },
        {
            "level_max": 0,
            "level_min": 0,
            "species": "SPECIES_NONE"
        },
        {
            "level_max": 0,
            "level_min": 0,
            "species": "SPECIES_NONE"
        },
        {
            "level_max": 0,
            "level_min": 0,
            "species": "SPECIES_NONE"
        }
    ],
    "super_rod_rate": 0,
    "super_rod_encounters": [
        {
            "level_max": 0,
            "level_min": 0,
            "species": "SPECIES_NONE"
        },
        {
            "level_max": 0,
            "level_min": 0,
            "species": "SPECIES_NONE"
        },
        {
            "level_max": 0,
            "level_min": 0,
            "species": "SPECIES_NONE"
        },
        {
            "level_max": 0,
            "level_min": 0,
            "species": "SPECIES_NONE"
        },
        {
            "level_max": 0,
            "level_min": 0,
            "species": "SPECIES_NONE"
        }
    ],
    "map_category": {
        "map_type": "dungeon",
        "map_number": 6
    }
}
