{
    "land_rate": 30,
    "land_encounters": [
        {
            "level": 23,
            "species": "SPECIES_GRIMER"
        },
        {
            "level": 21,
            "species": "SPECIES_EXEGGCUTE"
        },
        {
            "level": 22,
            "species": "SPECIES_DROWZEE"
        },
        {
            "level": 22,
            "species": "SPECIES_STUNKY"
        },
        {
            "level": 23,
            "species": "SPECIES_ARON"
        },
        {
            "level": 23,
            "species": "SPECIES_SPOINK"
        },
        {
            "level": 24,
            "species": "SPECIES_VOLTORB"
        },
        {
            "level": 21,
            "species": "SPECIES_TEDDIURSA"
        },
        {
            "level": 24,
            "species": "SPECIES_SKORUPI"
        },
        {
            "level": 24,
            "species": "SPECIES_HIPPOPOTAS"
        },
        {
            "level": 24,
            "species": "SPECIES_DELIBIRD"
        },
        {
            "level": 24,
            "species": "SPECIES_HOUNDOUR"
        }
    ],
    "swarms": [
        "SPECIES_SKORUPI",
        "SPECIES_HIPPOPOTAS"
    ],
    "day": [
        "SPECIES_GRIMER",
        "SPECIES_EXEGGCUTE"
    ],
    "night": [
        "SPECIES_DROWZEE",
        "SPECIES_STUNKY"
    ],
    "radar": [
        "SPECIES_ARON",
        "SPECIES_SPOINK",
        "SPECIES_VOLTORB",
        "SPECIES_TEDDIURSA"
    ],
    "rate_form0": 100,
    "rate_form1": 100,
    "rate_form2": 0,
    "rate_form3": 0,
    "rate_form4": 0,
    "unown_table": 0,
    "ruby": [
        "SPECIES_HOUNDOUR",
        "SPECIES_RHYHORN"
    ],
    "sapphire": [
        "SPECIES_HOUNDOUR",
        "SPECIES_RHYHORN"
    ],
    "emerald": [
        "SPECIES_HOUNDOUR",
        "SPECIES_RHYHORN"
    ],
    "firered": [
        "SPECIES_HOUNDOUR",
        "SPECIES_RHYHORN"
    ],
    "leafgreen": [
        "SPECIES_VULPIX",
        "SPECIES_VULPIX"
    ],
    "surf_rate": 10,
    "surf_encounters": [
        {
            "level_max": 30,
            "level_min": 20,
            "species": "SPECIES_FINNEON"
        },
        {
            "level_max": 30,
            "level_min": 20,
            "species": "SPECIES_CHINCHOU"
        },
        {
            "level_max": 40,
            "level_min": 20,
            "species": "SPECIES_LUVDISC"
        },
        {
            "level_max": 40,
            "level_min": 20,
            "species": "SPECIES_TENTACOOL"
        },
        {
            "level_max": 40,
            "level_min": 20,
            "species": "SPECIES_STARYU"
        }
    ],
    "old_rod_rate": 25,
    "old_rod_encounters": [
        {
            "level_max": 6,
            "level_min": 4,
            "species": "SPECIES_LOMBRE"
        },
        {
            "level_max": 7,
            "level_min": 3,
            "species": "SPECIES_CLAMPERL"
        },
        {
            "level_max": 10,
            "level_min": 5,
            "species": "SPECIES_MANTYKE"
        },
        {
            "level_max": 10,
            "level_min": 5,
            "species": "SPECIES_CORSOLA"
        },
        {
            "level_max": 15,
            "level_min": 5,
            "species": "SPECIES_POLIWHIRL"
        }
    ],
    "good_rod_rate": 50,
    "good_rod_encounters": [
        {
            "level_max": 20,
            "level_min": 15,
            "species": "SPECIES_WAILMER"
        },
        {
            "level_max": 20,
            "level_min": 15,
            "species": "SPECIES_PRINPLUP"
        },
        {
            "level_max": 25,
            "level_min": 10,
            "species": "SPECIES_MARSHTOMP"
        },
        {
            "level_max": 25,
            "level_min": 10,
            "species": "SPECIES_CROCONAW"
        },
        {
            "level_max": 25,
            "level_min": 10,
            "species": "SPECIES_WARTORTLE"
        }
    ],
    "super_rod_rate": 75,
    "super_rod_encounters": [
        {
            "level_max": 40,
            "level_min": 30,
            "species": "SPECIES_AZUMARILL"
        },
        {
            "level_max": 40,
            "level_min": 30,
            "species": "SPECIES_PELIPPER"
        },
        {
            "level_max": 55,
            "level_min": 40,
            "species": "SPECIES_QWILFISH"
        },
        {
            "level_max": 55,
            "level_min": 40,
            "species": "SPECIES_QUAGSIRE"
        },
        {
            "level_max": 55,
            "level_min": 40,
            "species": "SPECIES_SEADRA"
        }
    ],
    "map_category": {
        "map_type": "field",
        "map_number": 30
    }
}
